requests_middleware/__init__.py
requests_middleware/middleware.py
requests_middleware/contrib/__init__.py
requests_middleware/contrib/cachecontrolware.py
requests_middleware/contrib/httpcacheware.py
requests_middleware/contrib/robotware.py
requests_middleware/contrib/sourceware.py
requests_middleware/contrib/sslware.py
requests_middleware/contrib/throttleware.py
requests_middleware-0.1.2.dist-info/DESCRIPTION.rst
requests_middleware-0.1.2.dist-info/METADATA
requests_middleware-0.1.2.dist-info/RECORD
requests_middleware-0.1.2.dist-info/WHEEL
requests_middleware-0.1.2.dist-info/metadata.json
requests_middleware-0.1.2.dist-info/top_level.txt
