Metadata-Version: 2.0
Name: requests-middleware
Version: 0.1.2
Summary: Composable HTTP middleware for requests
Home-page: https://github.com/jmcarp/requests-middleware
Author: Joshua Carp
Author-email: jm.carp@gmail.com
License: Copyright 2014 Joshua Carp
Requires-Dist: httpcache
Requires-Dist: python-dateutil
Requires-Dist: reppy
Requires-Dist: requests
Requires-Dist: six
